{
  "consumes": [
    "application/json"
  ],
  "produces": [
    "application/json"
  ],
  "schemes": [
    "https"
  ],
  "swagger": "2.0",
  "info": {
    "title": "pay_gate",
    "version": "v1"
  },
  "basePath": "/",
  "paths": {
    "/api/pay_gate/get_user_info": {
      "post": {
        "consumes": [
          "application/json"
        ],
        "produces": [
          "application/json"
        ],
        "schemes": [
          "https"
        ],
        "summary": "get_user_info",
        "operationId": "payGateGetUserInfo",
        "parameters": [
          {
            "name": "body",
            "in": "body",
            "required": true,
            "schema": {
              "type": "object",
              "properties": {
                "user_id": {
                  "type": "string"
                }
              }
            }
          }
        ],
        "responses": {
          "200": {
            "description": "",
            "schema": {
              "type": "object",
              "properties": {
                "user_id": {
                  "type": "string"
                }
              }
            }
          }
        }
      }
    },
    "/api/pay_gate/health": {
      "post": {
        "consumes": [
          "application/x-www-form-urlencoded"
        ],
        "produces": [
          "application/json"
        ],
        "schemes": [
          "https"
        ],
        "summary": "health",
        "operationId": "payGateHealth",
        "responses": {
          "200": {
            "description": "",
            "schema": {
              "type": "object"
            }
          }
        }
      }
    }
  },
  "x-date": "2026-07-07 19:41:41",
  "x-description": "This is a goctl generated swagger file.",
  "x-github": "https://github.com/zeromicro/go-zero",
  "x-go-zero-doc": "https://go-zero.dev/",
  "x-goctl-version": "1.10.1"
}